webscreenshot/__init__.py
webscreenshot/requirements.txt
webscreenshot/webscreenshot.js
webscreenshot/webscreenshot.py
webscreenshot-2.97.dist-info/licenses/LICENSE
webscreenshot-2.97.dist-info/METADATA
webscreenshot-2.97.dist-info/WHEEL
webscreenshot-2.97.dist-info/entry_points.txt
webscreenshot-2.97.dist-info/top_level.txt
webscreenshot-2.97.dist-info/RECORD
