Metadata-Version: 2.4
Name: webscreenshot
Version: 2.97
Summary: A simple script to screenshot a list of websites
Author-email: tdebize@mail.com
License-Expression: LGPL-3.0-or-later
Project-URL: Homepage, https://github.com/maaaaz/webscreenshot
Keywords: webscreenshot,web,screenshot,phantomjs,chrome,edge,chromium,firefox,lazy,rendering,cli
Classifier: Topic :: Security
Classifier: Programming Language :: Python :: 3
Requires-Python: >=3
License-File: LICENSE
Dynamic: license-file
